cedashtools/__init__.py
cedashtools/user_access/__init__.py
cedashtools/user_access/encryption.py
cedashtools/user_access/validation.py
cedashtools/user_access/website.py
cedashtools-0.3.0.dist-info/LICENSE
cedashtools-0.3.0.dist-info/METADATA
cedashtools-0.3.0.dist-info/WHEEL
cedashtools-0.3.0.dist-info/top_level.txt
cedashtools-0.3.0.dist-info/RECORD
