Metadata-Version: 2.1
Name: cedashtools
Version: 0.3.0
Summary: For use in your Centric Engineers tools
Author-email: Centric Engineers <admin@centricengineers.com>
License: The MIT License (MIT)
Project-URL: Homepage, https://github.com/CentricEngineers/cedashtools.git
Keywords: Centric Engineers
Classifier: License :: OSI Approved :: MIT License
Classifier: Programming Language :: Python
Classifier: Programming Language :: Python :: 3
Requires-Python: >=3.8
License-File: LICENSE
Requires-Dist: requests==2.32.3
Requires-Dist: tenacity==9.0.0
Requires-Dist: cryptography==43.0.1
